certn/__init__.py
certn/client.py
certn/errors.py
certn/requester.py
certn/version.py
certn/api/__init__.py
certn/api/api.py
certn/api/applicants.py
certn/api/applications.py
certn/api/auth.py
certn/api/listings.py
certn/api/properties.py
certn/api/reports.py
certn_python-1.2.3.dist-info/LICENSE
certn_python-1.2.3.dist-info/METADATA
certn_python-1.2.3.dist-info/WHEEL
certn_python-1.2.3.dist-info/top_level.txt
certn_python-1.2.3.dist-info/RECORD
