Metadata-Version: 2.1
Name: certn-python
Version: 1.2.3
Summary: A python client for Certn API
Home-page: https://github.com/livebungalow/certn-python-public
Author: Bungalow Living
Author-email: engineering@bungalow.com
License: MIT
Platform: UNKNOWN
Classifier: Development Status :: 2 - Pre-Alpha
Classifier: License :: OSI Approved :: MIT License
Classifier: Programming Language :: Python
Classifier: Programming Language :: Python :: 3.6
Classifier: Programming Language :: Python :: 3.7
Requires-Dist: requests (<3,>=2)
